librosa/__init__.py
librosa/__init__.pyi
librosa/_cache.py
librosa/_typing.py
librosa/beat.py
librosa/decompose.py
librosa/display.py
librosa/effects.py
librosa/filters.py
librosa/onset.py
librosa/py.typed
librosa/segment.py
librosa/sequence.py
librosa/version.py
librosa/core/__init__.py
librosa/core/__init__.pyi
librosa/core/audio.py
librosa/core/constantq.py
librosa/core/convert.py
librosa/core/fft.py
librosa/core/harmonic.py
librosa/core/intervals.msgpack
librosa/core/intervals.py
librosa/core/notation.py
librosa/core/pitch.py
librosa/core/spectrum.py
librosa/feature/__init__.py
librosa/feature/__init__.pyi
librosa/feature/inverse.py
librosa/feature/rhythm.py
librosa/feature/spectral.py
librosa/feature/utils.py
librosa/util/__init__.py
librosa/util/__init__.pyi
librosa/util/_nnls.py
librosa/util/decorators.py
librosa/util/deprecation.py
librosa/util/exceptions.py
librosa/util/files.py
librosa/util/matching.py
librosa/util/utils.py
librosa/util/example_data/__init__.py
librosa/util/example_data/index.json
librosa/util/example_data/registry.txt
librosa-0.10.2.post1.dist-info/LICENSE.md
librosa-0.10.2.post1.dist-info/METADATA
librosa-0.10.2.post1.dist-info/WHEEL
librosa-0.10.2.post1.dist-info/top_level.txt
librosa-0.10.2.post1.dist-info/RECORD
