Metadata-Version: 2.1
Name: librosa
Version: 0.10.2.post1
Summary: Python module for audio and music processing
Home-page: https://librosa.org
Author: Brian McFee, librosa development team
Author-email: brian.mcfee@nyu.edu
License: ISC
Project-URL: Documentation, https://librosa.org/doc
Project-URL: Download, https://github.com/librosa/librosa/releases
Project-URL: Source, https://github.com/librosa/librosa
Project-URL: Tracker, https://github.com/librosa/librosa/issues
Project-URL: Discussion forum, https://groups.google.com/g/librosa
Classifier: License :: OSI Approved :: ISC License (ISCL)
Classifier: Programming Language :: Python
Classifier: Development Status :: 3 - Alpha
Classifier: Intended Audience :: Developers
Classifier: Topic :: Multimedia :: Sound/Audio :: Analysis
Classifier: Framework :: Matplotlib
Classifier: Programming Language :: Python :: 3
Classifier: Programming Language :: Python :: 3.7
Classifier: Programming Language :: Python :: 3.8
Classifier: Programming Language :: Python :: 3.9
Classifier: Programming Language :: Python :: 3.10
Classifier: Programming Language :: Python :: 3.11
Classifier: Programming Language :: Python :: 3.12
Requires-Python: >=3.7
License-File: LICENSE.md
Requires-Dist: audioread>=2.1.9
Requires-Dist: numpy!=1.22.0,!=1.22.1,!=1.22.2,>=1.20.3
Requires-Dist: scipy>=1.2.0
Requires-Dist: scikit-learn>=0.20.0
Requires-Dist: joblib>=0.14
Requires-Dist: decorator>=4.3.0
Requires-Dist: numba>=0.51.0
Requires-Dist: soundfile>=0.12.1
Requires-Dist: pooch>=1.1
Requires-Dist: soxr>=0.3.2
Requires-Dist: typing_extensions>=4.1.1
Requires-Dist: lazy_loader>=0.1
Requires-Dist: msgpack>=1.0
Provides-Extra: docs
Requires-Dist: numpydoc; extra == "docs"
Requires-Dist: sphinx!=1.3.1; extra == "docs"
Requires-Dist: sphinx_rtd_theme>=1.2.0; extra == "docs"
Requires-Dist: numba>=0.51; extra == "docs"
Requires-Dist: matplotlib>=3.5.0; extra == "docs"
Requires-Dist: sphinx-multiversion>=0.2.3; extra == "docs"
Requires-Dist: sphinx-gallery>=0.7; extra == "docs"
Requires-Dist: mir_eval>=0.5; extra == "docs"
Requires-Dist: ipython>=7.0; extra == "docs"
Requires-Dist: sphinxcontrib-svg2pdfconverter; extra == "docs"
Requires-Dist: presets; extra == "docs"
Requires-Dist: sphinx-copybutton>=0.5.2; extra == "docs"
Provides-Extra: tests
Requires-Dist: matplotlib>=3.5.0; extra == "tests"
Requires-Dist: packaging>=20.0; extra == "tests"
Requires-Dist: pytest-mpl; extra == "tests"
Requires-Dist: pytest-cov; extra == "tests"
Requires-Dist: pytest; extra == "tests"
Requires-Dist: samplerate; extra == "tests"
Requires-Dist: resampy>=0.2.2; extra == "tests"
Requires-Dist: types-decorator; extra == "tests"
Provides-Extra: display
Requires-Dist: matplotlib>=3.5.0; extra == "display"
